odoo/addons/maintenance_request_repair/README.rst
odoo/addons/maintenance_request_repair/__init__.py
odoo/addons/maintenance_request_repair/__manifest__.py
odoo/addons/maintenance_request_repair/i18n/es.po
odoo/addons/maintenance_request_repair/i18n/it.po
odoo/addons/maintenance_request_repair/i18n/maintenance_request_repair.pot
odoo/addons/maintenance_request_repair/i18n/pt_BR.po
odoo/addons/maintenance_request_repair/models/__init__.py
odoo/addons/maintenance_request_repair/models/maintenance_request.py
odoo/addons/maintenance_request_repair/models/repair_order.py
odoo/addons/maintenance_request_repair/readme/CONTRIBUTORS.md
odoo/addons/maintenance_request_repair/readme/DESCRIPTION.md
odoo/addons/maintenance_request_repair/readme/USAGE.md
odoo/addons/maintenance_request_repair/static/description/icon.png
odoo/addons/maintenance_request_repair/static/description/index.html
odoo/addons/maintenance_request_repair/tests/__init__.py
odoo/addons/maintenance_request_repair/tests/test_repair_order.py
odoo/addons/maintenance_request_repair/views/maintenance_request.xml
odoo/addons/maintenance_request_repair/views/repair_order.xml
odoo_addon_maintenance_request_repair-18.0.1.0.0.2.dist-info/METADATA
odoo_addon_maintenance_request_repair-18.0.1.0.0.2.dist-info/WHEEL
odoo_addon_maintenance_request_repair-18.0.1.0.0.2.dist-info/top_level.txt
odoo_addon_maintenance_request_repair-18.0.1.0.0.2.dist-info/RECORD
